netbox_bgp/__init__.py
netbox_bgp/admin.py
netbox_bgp/choices.py
netbox_bgp/filtersets.py
netbox_bgp/forms.py
netbox_bgp/models.py
netbox_bgp/navigation.py
netbox_bgp/tables.py
netbox_bgp/template_content.py
netbox_bgp/urls.py
netbox_bgp/version.py
netbox_bgp/views.py
netbox_bgp/api/__init__.py
netbox_bgp/api/serializers.py
netbox_bgp/api/urls.py
netbox_bgp/api/views.py
netbox_bgp/graphql/__init__.py
netbox_bgp/graphql/enums.py
netbox_bgp/graphql/filters.py
netbox_bgp/graphql/schema.py
netbox_bgp/graphql/types.py
netbox_bgp/migrations/0001_initial.py
netbox_bgp/migrations/0002_netbox_bgp.py
netbox_bgp/migrations/0003_netbox_bgp.py
netbox_bgp/migrations/0004_netbox_bgp.py
netbox_bgp/migrations/0005_netbox_bgp.py
netbox_bgp/migrations/0006_netbox_bgp.py
netbox_bgp/migrations/0007_netbox_bgp.py
netbox_bgp/migrations/0008_netbox_bgp.py
netbox_bgp/migrations/0009_netbox_bgp.py
netbox_bgp/migrations/0010_netbox_bgp.py
netbox_bgp/migrations/0011_netbox_bgp.py
netbox_bgp/migrations/0012_netbox_bgp.py
netbox_bgp/migrations/0013_netbox_bgp.py
netbox_bgp/migrations/0014_netbox_bgp.py
netbox_bgp/migrations/0015_netbox_bgp.py
netbox_bgp/migrations/0016_netbox_bgp.py
netbox_bgp/migrations/0017_netbox_bgp.py
netbox_bgp/migrations/0018_netbox_bgp.py
netbox_bgp/migrations/0019_netbox_bgp.py
netbox_bgp/migrations/0020_netbox_bgp.py
netbox_bgp/migrations/0021_netbox32_support.py
netbox_bgp/migrations/0022_netbox_bgp.py
netbox_bgp/migrations/0023_netbox_bgp.py
netbox_bgp/migrations/0024_netbox_bgp.py
netbox_bgp/migrations/0025_netbox_bgp.py
netbox_bgp/migrations/0026_netbox_bgp.py
netbox_bgp/migrations/0027_netbox_bgp.py
netbox_bgp/migrations/0028_netbox_bgp.py
netbox_bgp/migrations/0029_netbox_bgp.py
netbox_bgp/migrations/0030_netbox_bgp_comments.py
netbox_bgp/migrations/0031_netbox_bgp.py
netbox_bgp/migrations/0032_netbox_bgp.py
netbox_bgp/migrations/0033_alter_bgpsession_unique_together_and_more.py
netbox_bgp-0.18.0.dist-info/licenses/LICENSE
netbox_bgp-0.18.0.dist-info/METADATA
netbox_bgp-0.18.0.dist-info/WHEEL
netbox_bgp-0.18.0.dist-info/top_level.txt
netbox_bgp-0.18.0.dist-info/RECORD
