Metadata-Version: 2.4
Name: netbox-bgp
Version: 0.18.0
Summary: BGP related stuff
Home-page: https://github.com/netbox-community/netbox-bgp
Author: Nikolay Yuzefovich
Author-email: mgk.kolek@gmail.com
Classifier: Development Status :: 5 - Production/Stable
Classifier: License :: OSI Approved :: Apache Software License
Classifier: Framework :: Django
Classifier: Programming Language :: Python :: 3
License-File: LICENSE
Dynamic: author
Dynamic: author-email
Dynamic: classifier
Dynamic: description
Dynamic: description-content-type
Dynamic: home-page
Dynamic: license-file
Dynamic: summary
